{
	"configurations" : 
	[
		{
			"directories" : 
			[
				{
					"build" : ".",
					"jsonFile" : "directory-.-Debug-d0094a50bb2071803777.json",
					"minimumCMakeVersion" : 
					{
						"string" : "3.23"
					},
					"projectIndex" : 0,
					"source" : ".",
					"targetIndexes" : 
					[
						0
					]
				}
			],
			"name" : "Debug",
			"projects" : 
			[
				{
					"directoryIndexes" : 
					[
						0
					],
					"name" : "lesson6",
					"targetIndexes" : 
					[
						0
					]
				}
			],
			"targets" : 
			[
				{
					"directoryIndex" : 0,
					"id" : "lesson6.pro::@6890427a1f51a3e7e1df",
					"jsonFile" : "target-lesson6.pro-Debug-aa61795ce474e7ac8953.json",
					"name" : "lesson6.pro",
					"projectIndex" : 0
				}
			]
		}
	],
	"kind" : "codemodel",
	"paths" : 
	{
		"build" : "D:/Apps/Programming/K/C projects/lesson6/cmake-build-debug",
		"source" : "D:/Apps/Programming/K/C projects/lesson6"
	},
	"version" : 
	{
		"major" : 2,
		"minor" : 4
	}
}
